LICENSE.txt
MANIFEST.in
README.rst
setup.py
jk_pathpatternmatcher/AbstractPatternMatcher.py
jk_pathpatternmatcher/PathPatternMatcher.py
jk_pathpatternmatcher/PathPatternsMatcher.py
jk_pathpatternmatcher/__init__.py
jk_pathpatternmatcher/pathpatternmatcher.py
jk_pathpatternmatcher.egg-info/PKG-INFO
jk_pathpatternmatcher.egg-info/SOURCES.txt
jk_pathpatternmatcher.egg-info/dependency_links.txt
jk_pathpatternmatcher.egg-info/not-zip-safe
jk_pathpatternmatcher.egg-info/top_level.txt