Metadata-Version: 1.1
Name: jk-pathpatternmatcher
Version: 0.2017.10.7
Summary: A python module to perform simple pattern matching on paths.
Home-page: https://github.com/jkpubsrc/python-module-jk-pathpatternmatcher
Author: Jürgen Knauth
Author-email: pubsrc@binary-overflow.de
License: Apache 2.0
Download-URL: https://github.com/jkpubsrc/python-module-jk-pathpatternmatcher/tarball/0.2017.10.7
Keywords: filesystem,pattern-matching
Platform: UNKNOWN
Classifier: Development Status :: 4 - Beta
Classifier: Programming Language :: Python :: 3.5
Classifier: License :: OSI Approved :: Apache Software License
